leval/__init__.py
leval/evaluator.py
leval/excs.py
leval/py.typed
leval/rewriter_evaluator.py
leval/rewriter_utils.py
leval/simple.py
leval/utils.py
leval/extras/__init__.py
leval/extras/common_boolean_evaluator.py
leval/universe/__init__.py
leval/universe/base.py
leval/universe/default.py
leval/universe/simple.py
leval/universe/verifier.py
leval/universe/weakly_typed.py
leval-1.3.0.dist-info/METADATA
leval-1.3.0.dist-info/WHEEL
leval-1.3.0.dist-info/licenses/LICENSE
leval-1.3.0.dist-info/RECORD
