Metadata-Version: 2.3
Name: leval
Version: 1.3.0
Summary: Limited evaluator
Project-URL: Homepage, https://github.com/valohai/leval
Author-email: Valohai <info@valohai.com>
License-Expression: MIT
License-File: LICENSE
Requires-Python: >=3.8
Provides-Extra: test
Requires-Dist: pytest-cov==2.10.1; extra == 'test'
Requires-Dist: pytest<7.0; extra == 'test'
